{
    "requests": 28,
    "vehicles": [
        {
            "id": 74,
            "trips": [
                {
                    "origin": 24,
                    "destination": 18,
                    "arrival": "09h11",
                    "patients": []
                },
                {
                    "origin": 18,
                    "destination": 49,
                    "arrival": "09h25",
                    "patients": [
                        102
                    ]
                },
                {
                    "origin": 49,
                    "destination": 11,
                    "arrival": "10h17",
                    "patients": []
                },
                {
                    "origin": 11,
                    "destination": 36,
                    "arrival": "10h33",
                    "patients": [
                        89
                    ]
                },
                {
                    "origin": 36,
                    "destination": 47,
                    "arrival": "10h45",
                    "patients": []
                },
                {
                    "origin": 47,
                    "destination": 22,
                    "arrival": "11h05",
                    "patients": [
                        100
                    ]
                },
                {
                    "origin": 22,
                    "destination": 50,
                    "arrival": "13h02",
                    "patients": []
                },
                {
                    "origin": 50,
                    "destination": 18,
                    "arrival": "13h16",
                    "patients": [
                        103
                    ]
                },
                {
                    "origin": 18,
                    "destination": 46,
                    "arrival": "13h28",
                    "patients": []
                },
                {
                    "origin": 46,
                    "destination": 21,
                    "arrival": "13h47",
                    "patients": [
                        99
                    ]
                },
                {
                    "origin": 21,
                    "destination": 29,
                    "arrival": "14h05",
                    "patients": []
                },
                {
                    "origin": 29,
                    "destination": 4,
                    "arrival": "14h28",
                    "patients": [
                        82
                    ]
                },
                {
                    "origin": 4,
                    "destination": 13,
                    "arrival": "14h54",
                    "patients": []
                },
                {
                    "origin": 13,
                    "destination": 72,
                    "arrival": "15h08",
                    "patients": [
                        124
                    ]
                },
                {
                    "origin": 72,
                    "destination": 4,
                    "arrival": "15h30",
                    "patients": []
                },
                {
                    "origin": 4,
                    "destination": 29,
                    "arrival": "15h53",
                    "patients": [
                        82
                    ]
                },
                {
                    "origin": 29,
                    "destination": 24,
                    "arrival": "16h09",
                    "patients": []
                }
            ]
        },
        {
            "id": 74,
            "trips": []
        },
        {
            "id": 75,
            "trips": [
                {
                    "origin": 24,
                    "destination": 25,
                    "arrival": "09h49",
                    "patients": []
                },
                {
                    "origin": 25,
                    "destination": 0,
                    "arrival": "10h16",
                    "patients": [
                        78
                    ]
                },
                {
                    "origin": 0,
                    "destination": 48,
                    "arrival": "12h45",
                    "patients": []
                },
                {
                    "origin": 48,
                    "destination": 3,
                    "arrival": "13h07",
                    "patients": [
                        101
                    ]
                },
                {
                    "origin": 3,
                    "destination": 23,
                    "arrival": "13h12",
                    "patients": [
                        101,
                        107
                    ]
                },
                {
                    "origin": 23,
                    "destination": 54,
                    "arrival": "13h20",
                    "patients": [
                        107
                    ]
                },
                {
                    "origin": 54,
                    "destination": 7,
                    "arrival": "13h34",
                    "patients": []
                },
                {
                    "origin": 7,
                    "destination": 60,
                    "arrival": "13h39",
                    "patients": [
                        113
                    ]
                },
                {
                    "origin": 60,
                    "destination": 55,
                    "arrival": "13h55",
                    "patients": []
                },
                {
                    "origin": 55,
                    "destination": 1,
                    "arrival": "14h10",
                    "patients": [
                        108
                    ]
                },
                {
                    "origin": 1,
                    "destination": 18,
                    "arrival": "14h36",
                    "patients": []
                },
                {
                    "origin": 18,
                    "destination": 50,
                    "arrival": "14h54",
                    "patients": [
                        103
                    ]
                },
                {
                    "origin": 50,
                    "destination": 13,
                    "arrival": "15h36",
                    "patients": []
                },
                {
                    "origin": 13,
                    "destination": 51,
                    "arrival": "15h54",
                    "patients": [
                        104
                    ]
                },
                {
                    "origin": 51,
                    "destination": 24,
                    "arrival": "16h03",
                    "patients": []
                }
            ]
        },
        {
            "id": 76,
            "trips": [
                {
                    "origin": 24,
                    "destination": 61,
                    "arrival": "08h05",
                    "patients": []
                },
                {
                    "origin": 61,
                    "destination": 18,
                    "arrival": "08h08",
                    "patients": [
                        114
                    ]
                },
                {
                    "origin": 18,
                    "destination": 36,
                    "arrival": "08h58",
                    "patients": []
                },
                {
                    "origin": 36,
                    "destination": 11,
                    "arrival": "09h14",
                    "patients": [
                        89
                    ]
                },
                {
                    "origin": 11,
                    "destination": 18,
                    "arrival": "09h30",
                    "patients": []
                },
                {
                    "origin": 18,
                    "destination": 61,
                    "arrival": "09h37",
                    "patients": [
                        114
                    ]
                },
                {
                    "origin": 61,
                    "destination": 54,
                    "arrival": "10h22",
                    "patients": []
                },
                {
                    "origin": 54,
                    "destination": 3,
                    "arrival": "10h24",
                    "patients": [
                        107
                    ]
                },
                {
                    "origin": 3,
                    "destination": 58,
                    "arrival": "11h13",
                    "patients": []
                },
                {
                    "origin": 58,
                    "destination": 21,
                    "arrival": "11h28",
                    "patients": [
                        111
                    ]
                },
                {
                    "origin": 21,
                    "destination": 72,
                    "arrival": "11h33",
                    "patients": []
                },
                {
                    "origin": 72,
                    "destination": 13,
                    "arrival": "11h47",
                    "patients": [
                        124
                    ]
                },
                {
                    "origin": 13,
                    "destination": 24,
                    "arrival": "12h00",
                    "patients": []
                },
                {
                    "origin": 24,
                    "destination": 32,
                    "arrival": "15h06",
                    "patients": []
                },
                {
                    "origin": 32,
                    "destination": 7,
                    "arrival": "15h20",
                    "patients": [
                        85
                    ]
                },
                {
                    "origin": 7,
                    "destination": 23,
                    "arrival": "15h34",
                    "patients": []
                },
                {
                    "origin": 23,
                    "destination": 48,
                    "arrival": "15h58",
                    "patients": [
                        101
                    ]
                },
                {
                    "origin": 48,
                    "destination": 21,
                    "arrival": "16h19",
                    "patients": []
                },
                {
                    "origin": 21,
                    "destination": 46,
                    "arrival": "16h38",
                    "patients": [
                        99
                    ]
                },
                {
                    "origin": 46,
                    "destination": 7,
                    "arrival": "17h47",
                    "patients": []
                },
                {
                    "origin": 7,
                    "destination": 32,
                    "arrival": "18h01",
                    "patients": [
                        85
                    ]
                },
                {
                    "origin": 32,
                    "destination": 24,
                    "arrival": "18h13",
                    "patients": []
                }
            ]
        }
    ]
}