{
    "requests": 30,
    "vehicles": [
        {
            "id": 107,
            "trips": [
                {
                    "origin": 48,
                    "destination": 89,
                    "arrival": "07h44",
                    "patients": []
                },
                {
                    "origin": 89,
                    "destination": 33,
                    "arrival": "08h02",
                    "patients": [
                        144
                    ]
                },
                {
                    "origin": 33,
                    "destination": 106,
                    "arrival": "08h59",
                    "patients": []
                },
                {
                    "origin": 106,
                    "destination": 47,
                    "arrival": "09h17",
                    "patients": [
                        158
                    ]
                },
                {
                    "origin": 47,
                    "destination": 75,
                    "arrival": "09h40",
                    "patients": []
                },
                {
                    "origin": 75,
                    "destination": 20,
                    "arrival": "10h07",
                    "patients": [
                        131
                    ]
                },
                {
                    "origin": 20,
                    "destination": 71,
                    "arrival": "10h17",
                    "patients": []
                },
                {
                    "origin": 71,
                    "destination": 16,
                    "arrival": "10h29",
                    "patients": [
                        127
                    ]
                },
                {
                    "origin": 16,
                    "destination": 20,
                    "arrival": "10h41",
                    "patients": []
                },
                {
                    "origin": 20,
                    "destination": 75,
                    "arrival": "11h00",
                    "patients": [
                        131
                    ]
                },
                {
                    "origin": 75,
                    "destination": 33,
                    "arrival": "11h08",
                    "patients": []
                },
                {
                    "origin": 33,
                    "destination": 90,
                    "arrival": "11h19",
                    "patients": [
                        144
                    ]
                },
                {
                    "origin": 90,
                    "destination": 101,
                    "arrival": "11h33",
                    "patients": []
                },
                {
                    "origin": 101,
                    "destination": 43,
                    "arrival": "11h48",
                    "patients": [
                        154
                    ]
                },
                {
                    "origin": 43,
                    "destination": 101,
                    "arrival": "12h50",
                    "patients": [
                        154
                    ]
                },
                {
                    "origin": 101,
                    "destination": 94,
                    "arrival": "13h06",
                    "patients": []
                },
                {
                    "origin": 94,
                    "destination": 37,
                    "arrival": "13h18",
                    "patients": [
                        148
                    ]
                },
                {
                    "origin": 37,
                    "destination": 27,
                    "arrival": "13h32",
                    "patients": []
                },
                {
                    "origin": 27,
                    "destination": 83,
                    "arrival": "13h41",
                    "patients": [
                        138
                    ]
                },
                {
                    "origin": 83,
                    "destination": 78,
                    "arrival": "13h53",
                    "patients": []
                },
                {
                    "origin": 78,
                    "destination": 23,
                    "arrival": "14h01",
                    "patients": [
                        134
                    ]
                },
                {
                    "origin": 23,
                    "destination": 80,
                    "arrival": "14h11",
                    "patients": []
                },
                {
                    "origin": 80,
                    "destination": 24,
                    "arrival": "14h23",
                    "patients": [
                        135
                    ]
                },
                {
                    "origin": 24,
                    "destination": 23,
                    "arrival": "14h31",
                    "patients": []
                },
                {
                    "origin": 23,
                    "destination": 79,
                    "arrival": "14h36",
                    "patients": [
                        134
                    ]
                },
                {
                    "origin": 79,
                    "destination": 86,
                    "arrival": "14h44",
                    "patients": []
                },
                {
                    "origin": 86,
                    "destination": 30,
                    "arrival": "14h57",
                    "patients": [
                        141
                    ]
                },
                {
                    "origin": 30,
                    "destination": 37,
                    "arrival": "16h17",
                    "patients": []
                },
                {
                    "origin": 37,
                    "destination": 94,
                    "arrival": "16h29",
                    "patients": [
                        148
                    ]
                },
                {
                    "origin": 94,
                    "destination": 30,
                    "arrival": "17h39",
                    "patients": []
                },
                {
                    "origin": 30,
                    "destination": 86,
                    "arrival": "17h52",
                    "patients": [
                        141
                    ]
                },
                {
                    "origin": 86,
                    "destination": 48,
                    "arrival": "18h00",
                    "patients": []
                }
            ]
        },
        {
            "id": 108,
            "trips": [
                {
                    "origin": 49,
                    "destination": 104,
                    "arrival": "07h55",
                    "patients": []
                },
                {
                    "origin": 104,
                    "destination": 46,
                    "arrival": "08h06",
                    "patients": [
                        157
                    ]
                },
                {
                    "origin": 46,
                    "destination": 82,
                    "arrival": "08h13",
                    "patients": []
                },
                {
                    "origin": 82,
                    "destination": 26,
                    "arrival": "08h26",
                    "patients": [
                        137
                    ]
                },
                {
                    "origin": 26,
                    "destination": 67,
                    "arrival": "08h49",
                    "patients": []
                },
                {
                    "origin": 67,
                    "destination": 12,
                    "arrival": "09h12",
                    "patients": [
                        123
                    ]
                },
                {
                    "origin": 12,
                    "destination": 88,
                    "arrival": "09h53",
                    "patients": []
                },
                {
                    "origin": 88,
                    "destination": 32,
                    "arrival": "10h09",
                    "patients": [
                        143
                    ]
                },
                {
                    "origin": 32,
                    "destination": 46,
                    "arrival": "11h06",
                    "patients": []
                },
                {
                    "origin": 46,
                    "destination": 105,
                    "arrival": "11h28",
                    "patients": [
                        157
                    ]
                },
                {
                    "origin": 105,
                    "destination": 72,
                    "arrival": "11h55",
                    "patients": []
                },
                {
                    "origin": 72,
                    "destination": 17,
                    "arrival": "12h12",
                    "patients": [
                        128
                    ]
                },
                {
                    "origin": 17,
                    "destination": 32,
                    "arrival": "12h42",
                    "patients": []
                },
                {
                    "origin": 32,
                    "destination": 88,
                    "arrival": "12h58",
                    "patients": [
                        143
                    ]
                },
                {
                    "origin": 88,
                    "destination": 17,
                    "arrival": "13h30",
                    "patients": []
                },
                {
                    "origin": 17,
                    "destination": 72,
                    "arrival": "13h47",
                    "patients": [
                        128
                    ]
                },
                {
                    "origin": 72,
                    "destination": 18,
                    "arrival": "13h58",
                    "patients": []
                },
                {
                    "origin": 18,
                    "destination": 73,
                    "arrival": "14h15",
                    "patients": [
                        129
                    ]
                },
                {
                    "origin": 73,
                    "destination": 40,
                    "arrival": "15h50",
                    "patients": []
                },
                {
                    "origin": 40,
                    "destination": 98,
                    "arrival": "16h05",
                    "patients": [
                        151
                    ]
                },
                {
                    "origin": 98,
                    "destination": 11,
                    "arrival": "16h19",
                    "patients": []
                },
                {
                    "origin": 11,
                    "destination": 66,
                    "arrival": "16h47",
                    "patients": [
                        122
                    ]
                },
                {
                    "origin": 66,
                    "destination": 49,
                    "arrival": "16h57",
                    "patients": []
                }
            ]
        },
        {
            "id": 109,
            "trips": [
                {
                    "origin": 50,
                    "destination": 95,
                    "arrival": "08h39",
                    "patients": []
                },
                {
                    "origin": 95,
                    "destination": 38,
                    "arrival": "08h54",
                    "patients": [
                        149
                    ]
                },
                {
                    "origin": 38,
                    "destination": 56,
                    "arrival": "09h12",
                    "patients": []
                },
                {
                    "origin": 56,
                    "destination": 2,
                    "arrival": "09h32",
                    "patients": [
                        113
                    ]
                },
                {
                    "origin": 2,
                    "destination": 12,
                    "arrival": "10h13",
                    "patients": []
                },
                {
                    "origin": 12,
                    "destination": 67,
                    "arrival": "10h25",
                    "patients": [
                        123
                    ]
                },
                {
                    "origin": 67,
                    "destination": 38,
                    "arrival": "10h45",
                    "patients": []
                },
                {
                    "origin": 38,
                    "destination": 95,
                    "arrival": "10h57",
                    "patients": [
                        149
                    ]
                },
                {
                    "origin": 95,
                    "destination": 2,
                    "arrival": "11h09",
                    "patients": []
                },
                {
                    "origin": 2,
                    "destination": 73,
                    "arrival": "11h13",
                    "patients": [
                        113
                    ]
                },
                {
                    "origin": 73,
                    "destination": 18,
                    "arrival": "11h27",
                    "patients": [
                        113,
                        129
                    ]
                },
                {
                    "origin": 18,
                    "destination": 56,
                    "arrival": "11h37",
                    "patients": [
                        113
                    ]
                },
                {
                    "origin": 56,
                    "destination": 58,
                    "arrival": "11h43",
                    "patients": []
                },
                {
                    "origin": 58,
                    "destination": 4,
                    "arrival": "11h59",
                    "patients": [
                        115
                    ]
                },
                {
                    "origin": 4,
                    "destination": 98,
                    "arrival": "12h35",
                    "patients": []
                },
                {
                    "origin": 98,
                    "destination": 40,
                    "arrival": "12h51",
                    "patients": [
                        151
                    ]
                },
                {
                    "origin": 40,
                    "destination": 66,
                    "arrival": "14h06",
                    "patients": []
                },
                {
                    "origin": 66,
                    "destination": 11,
                    "arrival": "14h25",
                    "patients": [
                        122
                    ]
                },
                {
                    "origin": 11,
                    "destination": 4,
                    "arrival": "14h32",
                    "patients": []
                },
                {
                    "origin": 4,
                    "destination": 58,
                    "arrival": "14h48",
                    "patients": [
                        115
                    ]
                },
                {
                    "origin": 58,
                    "destination": 50,
                    "arrival": "15h00",
                    "patients": []
                }
            ]
        },
        {
            "id": 109,
            "trips": []
        }
    ]
}